README.md
setup.cfg
setup.py
ghsprint/__init__.py
ghsprint/__main__.py
ghsprint/board_card.py
ghsprint/board_stuff.py
ghsprint/ghdriver.py
ghsprint/issue.py
ghsprint/issue_event.py
ghsprint/pr_stuff.py
ghsprint/repo_stuff.py
ghsprint/request_session.py
ghsprint/sprint.py
ghsprint/utils.py
ghsprint.egg-info/PKG-INFO
ghsprint.egg-info/SOURCES.txt
ghsprint.egg-info/dependency_links.txt
ghsprint.egg-info/requires.txt
ghsprint.egg-info/top_level.txt