Metadata-Version: 2.1
Name: ghsprint
Version: 0.4
Summary: Contains utilities for agile sprints that use the GitHub platform.
Home-page: https://github.com/AlxndrJhn/ghsprint
Author: Alexander Jahn
Author-email: jahn.alexander@gmail.com
License: GNU GPLv3
Download-URL: https://github.com/AlxndrJhn/ghsprint/archive/0.1.tar.gz
Keywords: GitHub,utilities,reporting,sprint
Platform: UNKNOWN
Classifier: Development Status :: 3 - Alpha
Classifier: Intended Audience :: Developers
Classifier: Topic :: Utilities
Classifier: License :: OSI Approved :: GNU General Public License v3 or later (GPLv3+)
Classifier: Programming Language :: Python :: 3.5
Classifier: Programming Language :: Python :: 3.6
Classifier: Programming Language :: Python :: 3.7
